setup.cfg
setup.py
hdv_dummy/__init__.py
hdv_dummy/dummy.py
hdv_dummy.egg-info/PKG-INFO
hdv_dummy.egg-info/SOURCES.txt
hdv_dummy.egg-info/dependency_links.txt
hdv_dummy.egg-info/top_level.txt