Metadata-Version: 1.1
Name: hdv-dummy
Version: 0.0.2
Summary: The object returns null value without any error
Home-page: https://github.com/jk43/hdv_dummy
Author: Alex Hyojun Kim
Author-email: alex@hotdev.com
License: BSD
Download-URL: https://github.com/jk43/hdv_dummy.git
Platform: UNKNOWN
